MANIFEST.in
Makefile
README.rst
setup.py
libsousou/__init__.py
libsousou/module_loading.py
libsousou/password.py
libsousou/translation.py
libsousou.egg-info/PKG-INFO
libsousou.egg-info/SOURCES.txt
libsousou.egg-info/dependency_links.txt
libsousou.egg-info/top_level.txt
libsousou/cli/__init__.py
libsousou/cli/argument.py
libsousou/cli/baseparser.py
libsousou/cli/command.py
libsousou/cli/test.py
libsousou/hashers/__init__.py
libsousou/hashers/base.py
libsousou/hashers/pbkdf2.py
libsousou/iana/__init__.py
libsousou/iana/pen.py
libsousou/meta/__init__.py
libsousou/meta/hybrid.py
libsousou/process/__init__.py
libsousou/process/loop.py
libsousou/process/utils.py
libsousou/translation/__init__.py
libsousou/web/__init__.py
libsousou/web/base.py
libsousou/web/contextmixin.py
libsousou/web/exc.py
libsousou/web/irequest.py
libsousou/web/rfc2616.py
tests/unit/test_cli.py
tests/unit/test_hashers.py
tests/unit/test_iana.py
tests/unit/test_misc.py
tests/unit/test_module_loading.py
tests/unit/test_password.py