Metadata-Version: 1.1
Name: libsousou
Version: 1.1.0
Summary: Sousou Industries application utility library
Home-page: UNKNOWN
Author: Sousou Industries
Author-email: releases@sousouindustries.com
License: UNKNOWN
Platform: UNKNOWN
Classifier: Development Status :: 3 - Alpha
Classifier: Environment :: Other Environment
Classifier: Intended Audience :: System Administrators
Classifier: Intended Audience :: Developers
Classifier: Operating System :: POSIX :: Linux
Classifier: Programming Language :: Python
Classifier: Programming Language :: Python :: 3.4
